My_proposed_adder_03/cla.v
// 4-bit Carry Lookahead Adder
module cla_4bit (
    input  [3:0] a, b,     // 4-bit inputs
    input        cin,      // Carry in
    output [3:0] sum,      // 4-bit sum
    output       cout      // Carry out
);

    wire [3:0] p, g;   // propagate and generate
    wire [4:1] c;      // internal carries

    // Propagate and Generate
    assign p = a ^ b;      // propagate = a XOR b
    assign g = a & b;      // generate  = a AND b

    // Carry Lookahead Logic
    assign c[1] = g[0] | (p[0] & cin);
    assign c[2] = g[1] | (p[1] & g[0]) | (p[1] & p[0] & cin);
    assign c[3] = g[2] | (p[2] & g[1]) | (p[2] & p[1] & g[0]) | (p[2] & p[1] & p[0] & cin);
    assign cout = g[3] | (p[3] & g[2]) | (p[3] & p[2] & g[1]) | (p[3] & p[2] & p[1] & g[0]) | (p[3] & p[2] & p[1] & p[0] & cin);

    // Sum calculation
    assign sum[0] = p[0] ^ cin;
    assign sum[1] = p[1] ^ c[1];
    assign sum[2] = p[2] ^ c[2];
    assign sum[3] = p[3] ^ c[3];

endmodule

My_proposed_adder_03/cla_tb.v
`timescale 1ns/1ps
`include "cla.v"

module tb_cla_4bit;

    reg  [3:0] a, b;
    reg        cin;
    wire [3:0] sum;
    wire       cout;

    // Instantiate DUT (Device Under Test)
    cla_4bit uut (
        .a(a),
        .b(b),
        .cin(cin),
        .sum(sum),
        .cout(cout)
    );

    // Test procedure
    initial begin
        $dumpfile("cla_4bit_tb.vcd"); // For waveform view (GTKWave)
        $dumpvars(0, tb_cla_4bit);

        // Monitor values
        $monitor("Time=%0t | a=%d b=%d cin=%d || sum=%d cout=%d", 
                  $time, a, b, cin, sum, cout);

        // Apply test vectors
        cin = 0; a = 4'b0000; b = 4'b0000; #10;
        cin = 1; a = 4'b0000; b = 4'b0000; #10;
        cin = 0; a = 4'b1010; b = 4'b0101; #10;
        cin = 1; a = 4'b1010; b = 4'b0101; #10;
        cin = 0; a = 4'b1111; b = 4'b0001; #10;
        cin = 1; a = 4'b1111; b = 4'b0001; #10;
        cin = 0; a = 4'b1111; b = 4'b1111; #10;
        cin = 1; a = 4'b1111; b = 4'b1111; #10;

        // Random test cases
        repeat(10) begin
            a   = $random % 16;   // 4-bit random
            b   = $random % 16;
            cin = $random % 2;
            #10;
        end

        $finish;
    end
endmodule

My_proposed_adder_03/cla_4bit_tb.vcd
$date
	Tue Aug 19 03:27:43 2025
$end
$version
	Icarus Verilog
$end
$timescale
	1ps
$end
$scope module tb_cla_4bit $end
$var wire 4 ! sum [3:0] $end
$var wire 1 " cout $end
$var reg 4 # a [3:0] $end
$var reg 4 $ b [3:0] $end
$var reg 1 % cin $end
$scope module uut $end
$var wire 4 & a [3:0] $end
$var wire 4 ' b [3:0] $end
$var wire 1 % cin $end
$var wire 1 " cout $end
$var wire 4 ( g [3:0] $end
$var wire 4 ) p [3:0] $end
$var wire 4 * sum [3:0] $end
$var wire 4 + c [4:1] $end
$upscope $end
$upscope $end
$enddefinitions $end
$comment Show the parameter values. $end
$dumpall
$end
#0
$dumpvars
bz000 +
b0 *
b0 )
b0 (
b0 '
b0 &
0%
b0 $
b0 #
0"
b0 !
$end
#10000
b1 !
b1 *
1%
#20000
b1111 )
b1111 !
b1111 *
b101 $
b101 '
b1010 #
b1010 &
0%
#30000
bz111 +
1"
b0 !
b0 *
1%
#40000
bz111 +
1"
b1110 )
b1 (
b0 !
b0 *
b1 $
b1 '
b1111 #
b1111 &
0%
#50000
b1 !
b1 *
1%
#60000
b0 )
b1111 (
b1110 !
b1110 *
b1111 $
b1111 '
0%
#70000
b1111 !
b1111 *
1%
#80000
0"
b110 !
b110 *
bz001 +
b101 )
b0 (
b1 $
b1 '
b100 #
b100 &
#90000
1"
bz111 +
b1 !
b1 *
b1110 )
b1 (
b1101 $
b1101 '
b11 #
b11 &
#100000
0"
b1000 !
b1000 *
bz111 +
b111 )
b0 (
b10 $
b10 '
b101 #
b101 &
#110000
1"
b100 !
b100 *
b1011 )
b100 (
b110 $
b110 '
b1101 #
b1101 &
#120000
bz101 +
b1010 !
b1010 *
b1 )
b1100 (
b1100 $
b1100 '
#130000
0"
bz100 +
b1011 !
b1011 *
b11 )
b100 (
0%
b101 $
b101 '
b110 #
b110 &
#140000
b1100 !
b1100 *
bz111 +
b10 )
b101 (
b111 $
b111 '
b101 #
b101 &
#150000
1"
b1 !
b1 *
bz110 +
b1101 )
b10 (
b10 $
b10 '
b1111 #
b1111 &
#160000
b1101 !
b1101 *
0"
bz000 +
b0 (
b101 $
b101 '
b1000 #
b1000 &
#170000
1"
bz101 +
b1011 !
b1011 *
b0 )
b1101 (
1%
b1101 $
b1101 '
b1101 #
b1101 &
