My_proposed_adder_1/brent_kung_adder.v
module brent_kung_adder_4bit (
    input  [3:0] a,
    input  [3:0] b,
    input        cin,
    output [3:0] sum,
    output       carry_out
);
    // Step 1: Propagate & Generate
    wire [3:0] p, g;
    assign p = a ^ b;  // Propagate
    assign g = a & b;  // Generate

    // Step 2: Prefix computation
    wire g1_0, g2_0, g3_0, g3_2;
    wire p1_0, p2_0, p3_0, p3_2;

    // Level 1
    assign g1_0 = g[1] | (p[1] & g[0]);
    assign p1_0 = p[1] & p[0];
    assign g3_2 = g[3] | (p[3] & g[2]);
    assign p3_2 = p[3] & p[2];

    // Level 2
    assign g2_0 = g[2] | (p[2] & g1_0);
    assign p2_0 = p[2] & p1_0;

    // Level 3
    assign g3_0 = g3_2 | (p3_2 & g2_0);
    assign p3_0 = p3_2 & p2_0;

    // Step 3: Carry computation (cin included)
    wire [4:0] carry;
    assign carry[0] = cin;
    assign carry[1] = g[0] | (p[0] & carry[0]);
    assign carry[2] = g1_0 | (p1_0 & carry[0]);
    assign carry[3] = g2_0 | (p2_0 & carry[0]);
    assign carry[4] = g3_0 | (p3_0 & carry[0]);

    // Step 4: Sum & Cout
    assign sum       = p ^ carry[3:0];
    assign carry_out = carry[4];
endmodule

My_proposed_adder_1/brent_kung_adder_tb.v
`timescale 1ns/1ps
`include "brent_kung_adder.v"

module tb_brent_kung_adder_4bit;
    reg  [3:0] a, b;
    reg        cin;
    wire [3:0] sum;
    wire       carry_out;

    // Instantiate DUT
    brent_kung_adder_4bit uut (
        .a(a),
        .b(b),
        .cin(cin),
        .sum(sum),
        .carry_out(carry_out)
    );

    initial begin
        $dumpfile("brent_kung_4bit.vcd");
        $dumpvars(0, tb_brent_kung_adder_4bit);

        $monitor("t=%0t | a=%b(%0d) b=%b(%0d) cin=%b | sum=%b(%0d) cout=%b",
                 $time, a, a, b, b, cin, sum, sum, carry_out);

        // Test all combinations
        for (integer i = 0; i < 16; i = i + 1) begin
            for (integer j = 0; j < 16; j = j + 1) begin
                for (integer k = 0; k < 2; k = k + 1) begin
                    a   = i;
                    b   = j;
                    cin = k;
                    #5;
                end
            end
        end
        $finish;
    end
endmodule

Brent_kung_adder/brent_kung_4bit.vcd
$date
	Fri Aug 15 17:31:52 2025
$end
$version
	Icarus Verilog
$end
$timescale
	1ps
$end
$scope module tb_brent_kung_adder_4bit $end
$var wire 4 ! sum [3:0] $end
$var wire 1 " carry_out $end
$var reg 4 # a [3:0] $end
$var reg 4 $ b [3:0] $end
$var reg 1 % cin $end
$scope module uut $end
$var wire 4 & a [3:0] $end
$var wire 4 ' b [3:0] $end
$var wire 1 % cin $end
$var wire 4 ( g [3:0] $end
$var wire 1 ) g1_0 $end
$var wire 1 * g2_0 $end
$var wire 1 + g3_0 $end
$var wire 1 , g3_2 $end
$var wire 4 - p [3:0] $end
$var wire 1 . p1_0 $end
$var wire 1 / p2_0 $end
$var wire 1 0 p3_0 $end
$var wire 1 1 p3_2 $end
$var wire 4 2 sum [3:0] $end
$var wire 1 " carry_out $end
$var wire 5 3 carry [4:0] $end
$upscope $end
$scope begin $ivl_for_loop0 $end
$var integer 32 4 i [31:0] $end
$scope begin $ivl_for_loop1 $end
$var integer 32 5 j [31:0] $end
$scope begin $ivl_for_loop2 $end
$var integer 32 6 k [31:0] $end
$upscope $end
$upscope $end
$upscope $end
$upscope $end
$enddefinitions $end
$comment Show the parameter values. $end
$dumpall
$end
#0
$dumpvars
b0 6
b0 5
b0 4
b0 3
b0 2
01
00
0/
0.
b0 -
0,
0+
0*
0)
b0 (
b0 '
b0 &
0%
b0 $
b0 #
0"
b0 !
$end
#5000
b1 !
b1 2
b1 3
1%
b1 6
#10000
b1 -
b0 3
0%
b1 $
b1 '
b1 5
b0 6
#15000
b10 !
b10 2
b11 3
1%
b1 6
#20000
b10 !
b10 2
b10 -
b0 3
0%
b10 $
b10 '
b10 5
b0 6
#25000
b11 !
b11 2
b1 3
1%
b1 6
#30000
1.
b11 -
b0 3
0%
b11 $
b11 '
b11 5
b0 6
#35000
b100 !
b100 2
b111 3
1%
b1 6
#40000
0.
0/
b100 !
b100 2
b100 -
b0 3
0%
b100 $
b100 '
b100 5
b0 6
#45000
b101 !
b101 2
b1 3
1%
b1 6
#50000
b101 -
b0 3
0%
b101 $
b101 '
b101 5
b0 6
#55000
b110 !
b110 2
b11 3
1%
b1 6
#60000
b110 !
b110 2
b110 -
b0 3
0%
b110 $
b110 '
b110 5
b0 6
#65000
b111 !
b111 2
b1 3
1%
b1 6
#70000
1/
1.
b111 -
b0 3
0%
b111 $
b111 '
b111 5
b0 6
#75000
b1000 !
b1000 2
b1111 3
1%
b1 6
#80000
0.
0/
b1000 !
b1000 2
b1000 -
b0 3
0%
b1000 $
b1000 '
b1000 5
b0 6
#85000
b1001 !
b1001 2
b1 3
1%
b1 6
#90000
b1001 -
b0 3
0%
b1001 $
b1001 '
b1001 5
b0 6
#95000
b1010 !
b1010 2
b11 3
1%
b1 6
#100000
b1010 !
b1010 2
b1010 -
b0 3
0%
b1010 $
b1010 '
b1010 5
b0 6
#105000
b1011 !
b1011 2
b1 3
1%
b1 6
#110000
1.
b1011 -
b0 3
0%
b1011 $
b1011 '
b1011 5
b0 6
#115000
b1100 !
b1100 2
b111 3
1%
b1 6
#120000
00
0.
11
0/
b1100 !
b1100 2
b1100 -
b0 3
0%
b1100 $
b1100 '
b1100 5
b0 6
#125000
b1101 !
b1101 2
b1 3
1%
b1 6
#130000
b1101 -
b0 3
0%
b1101 $
b1101 '
b1101 5
b0 6
#135000
b1110 !
b1110 2
b11 3
1%
b1 6
#140000
b1110 !
b1110 2
b1110 -
b0 3
0%
b1110 $
b1110 '
b1110 5
b0 6
#145000
b1111 !
b1111 2
b1 3
1%
b1 6
#150000
10
1/
1.
b1111 -
b0 3
0%
b1111 $
b1111 '
b1111 5
b0 6
#155000
1"
b0 !
b0 2
b11111 3
1%
b1 6
#160000
0"
00
0.
01
0/
b1 !
b1 2
b1 -
b0 3
0%
b0 $
b0 '
b1 #
b1 &
b1 4
b0 5
b0 6
#165000
b10 !
b10 2
b11 3
1%
b1 6
#170000
b0 -
b1 (
b10 3
0%
b1 $
b1 '
b1 5
b0 6
#175000
b11 !
b11 2
b11 3
1%
b1 6
#180000
1.
b11 !
b11 2
b11 -
b0 (
b0 3
0%
b10 $
b10 '
b10 5
b0 6
#185000
b100 !
b100 2
b111 3
1%
b1 6
#190000
b100 !
b100 2
1)
0.
b10 -
b1 (
b110 3
0%
b11 $
b11 '
b11 5
b0 6
#195000
b101 !
b101 2
b111 3
1%
b1 6
#200000
0*
0)
b101 !
b101 2
b101 -
b0 (
b0 3
0%
b100 $
b100 '
b100 5
b0 6
#205000
b110 !
b110 2
b11 3
1%
b1 6
#210000
b100 -
b1 (
b10 3
0%
b101 $
b101 '
b101 5
b0 6
#215000
b111 !
b111 2
b11 3
1%
b1 6
#220000
1/
1.
b111 !
b111 2
b111 -
b0 (
b0 3
0%
b110 $
b110 '
b110 5
b0 6
#225000
b1000 !
b1000 2
b1111 3
1%
b1 6
#230000
1*
b1000 !
b1000 2
0/
1)
0.
b110 -
b1 (
b1110 3
0%
b111 $
b111 '
b111 5
b0 6
#235000
b1001 !
b1001 2
b1111 3
1%
b1 6
#240000
0*
0)
b1001 !
b1001 2
b1001 -
b0 (
b0 3
0%
b1000 $
b1000 '
b1000 5
b0 6
#245000
b1010 !
b1010 2
b11 3
1%
b1 6
#250000
b1000 -
b1 (
b10 3
0%
b1001 $
b1001 '
b1001 5
b0 6
#255000
b1011 !
b1011 2
b11 3
1%
b1 6
#260000
1.
b1011 !
b1011 2
b1011 -
b0 (
b0 3
0%
b1010 $
b1010 '
b1010 5
b0 6
#265000
b1100 !
b1100 2
b111 3
1%
b1 6
#270000
b1100 !
b1100 2
1)
0.
b1010 -
b1 (
b110 3
0%
b1011 $
b1011 '
b1011 5
b0 6
#275000
b1101 !
b1101 2
b111 3
1%
b1 6
#280000
0"
0+
0*
0)
11
b1101 !
b1101 2
b1101 -
b0 (
b0 3
0%
b1100 $
b1100 '
b1100 5
b0 6
#285000
b1110 !
b1110 2
b11 3
1%
b1 6
#290000
b1100 -
b1 (
b10 3
0%
b1101 $
b1101 '
b1101 5
b0 6
#295000
b1111 !
b1111 2
b11 3
1%
b1 6
#300000
10
1/
1.
b1111 !
b1111 2
b1111 -
b0 (
b0 3
0%
b1110 $
b1110 '
b1110 5
b0 6
#305000
1"
b0 !
b0 2
b11111 3
1%
b1 6
#310000
1+
1*
b0 !
b0 2
00
1"
0/
1)
0.
b1110 -
b1 (
b11110 3
0%
b1111 $
b1111 '
b1111 5
b0 6
#315000
b1 !
b1 2
b11111 3
1%
b1 6
#320000
0"
0+
0*
0)
01
b10 !
b10 2
b10 -
b0 (
b0 3
0%
b0 $
b0 '
b10 #
b10 &
b10 4
b0 5
b0 6
#325000
b11 !
b11 2
b1 3
1%
b1 6
#330000
1.
b11 -
b0 3
0%
b1 $
b1 '
b1 5
b0 6
#335000
b100 !
b100 2
b111 3
1%
b1 6
#340000
0.
1)
b100 !
b100 2
b0 -
b10 (
b100 3
0%
b10 $
b10 '
b10 5
b0 6
#345000
b101 !
b101 2
b101 3
1%
b1 6
#350000
b1 -
b100 3
0%
b11 $
b11 '
b11 5
b0 6
#355000
b110 !
b110 2
b111 3
1%
b1 6
#360000
0)
b110 !
b110 2
b110 -
b0 (
b0 3
0%
b100 $
b100 '
b100 5
b0 6
#365000
b111 !
b111 2
b1 3
1%
b1 6
#370000
1/
1.
b111 -
b0 3
0%
b101 $
b101 '
b101 5
b0 6
#375000
b1000 !
b1000 2
b1111 3
1%
b1 6
#380000
1*
0/
0.
1)
b1000 !
b1000 2
b100 -
b10 (
b1100 3
0%
b110 $
b110 '
b110 5
b0 6
#385000
b1001 !
b1001 2
b1101 3
1%
b1 6
#390000
b101 -
b1100 3
0%
b111 $
b111 '
b111 5
b0 6
#395000
b1010 !
b1010 2
b1111 3
1%
b1 6
#400000
0*
0)
b1010 !
b1010 2
b1010 -
b0 (
b0 3
0%
b1000 $
b1000 '
b1000 5
b0 6
#405000
b1011 !
b1011 2
b1 3
1%
b1 6
#410000
1.
b1011 -
b0 3
0%
b1001 $
b1001 '
b1001 5
b0 6
#415000
b1100 !
b1100 2
b111 3
1%
b1 6
#420000
0.
1)
b1100 !
b1100 2
b1000 -
b10 (
b100 3
0%
b1010 $
b1010 '
b1010 5
b0 6
#425000
b1101 !
b1101 2
b101 3
1%
b1 6
#430000
b1001 -
b100 3
0%
b1011 $
b1011 '
b1011 5
b0 6
#435000
b1110 !
b1110 2
b111 3
1%
b1 6
#440000
11
0)
b1110 !
b1110 2
b1110 -
b0 (
b0 3
0%
b1100 $
b1100 '
b1100 5
b0 6
#445000
b1111 !
b1111 2
b1 3
1%
b1 6
#450000
10
1/
1.
b1111 -
b0 3
0%
b1101 $
b1101 '
b1101 5
b0 6
#455000
1"
b0 !
b0 2
b11111 3
1%
b1 6
#460000
1+
00
1*
1"
0/
0.
1)
b0 !
b0 2
b1100 -
b10 (
b11100 3
0%
b1110 $
b1110 '
b1110 5
b0 6
#465000
b1 !
b1 2
b11101 3
1%
b1 6
#470000
b1101 -
b11100 3
0%
b1111 $
b1111 '
b1111 5
b0 6
#475000
b10 !
b10 2
b11111 3
1%
b1 6
#480000
0"
0+
0*
1.
01
0)
b11 !
b11 2
b11 -
b0 (
b0 3
0%
b0 $
b0 '
b11 #
b11 &
b11 4
b0 5
b0 6
#485000
b100 !
b100 2
b111 3
1%
b1 6
#490000
b100 !
b100 2
1)
0.
b10 -
b1 (
b110 3
0%
b1 $
b1 '
b1 5
b0 6
#495000
b101 !
b101 2
b111 3
1%
b1 6
#500000
b101 !
b101 2
b1 -
b10 (
b100 3
0%
b10 $
b10 '
b10 5
b0 6
#505000
b110 !
b110 2
b111 3
1%
b1 6
#510000
b0 -
b11 (
b110 3
0%
b11 $
b11 '
b11 5
b0 6
#515000
b111 !
b111 2
b111 3
1%
b1 6
#520000
1/
1.
0)
b111 !
b111 2
b111 -
b0 (
b0 3
0%
b100 $
b100 '
b100 5
b0 6
#525000
b1000 !
b1000 2
b1111 3
1%
b1 6
#530000
1*
b1000 !
b1000 2
0/
1)
0.
b110 -
b1 (
b1110 3
0%
b101 $
b101 '
b101 5
b0 6
#535000
b1001 !
b1001 2
b1111 3
1%
b1 6
#540000
b1001 !
b1001 2
b101 -
b10 (
b1100 3
0%
b110 $
b110 '
b110 5
b0 6
#545000
b1010 !
b1010 2
b1111 3
1%
b1 6
#550000
b100 -
b11 (
b1110 3
0%
b111 $
b111 '
b111 5
b0 6
#555000
b1011 !
b1011 2
b1111 3
1%
b1 6
#560000
0*
1.
0)
b1011 !
b1011 2
b1011 -
b0 (
b0 3
0%
b1000 $
b1000 '
b1000 5
b0 6
#565000
b1100 !
b1100 2
b111 3
1%
b1 6
#570000
b1100 !
b1100 2
1)
0.
b1010 -
b1 (
b110 3
0%
b1001 $
b1001 '
b1001 5
b0 6
#575000
b1101 !
b1101 2
b111 3
1%
b1 6
#580000
b1101 !
b1101 2
b1001 -
b10 (
b100 3
0%
b1010 $
b1010 '
b1010 5
b0 6
#585000
b1110 !
b1110 2
b111 3
1%
b1 6
#590000
b1000 -
b11 (
b110 3
0%
b1011 $
b1011 '
b1011 5
b0 6
#595000
b1111 !
b1111 2
b111 3
1%
b1 6
#600000
10
1/
1.
11
0)
b1111 !
b1111 2
b1111 -
b0 (
b0 3
0%
b1100 $
b1100 '
b1100 5
b0 6
#605000
1"
b0 !
b0 2
b11111 3
1%
b1 6
#610000
1+
1*
b0 !
b0 2
00
1"
0/
1)
0.
b1110 -
b1 (
b11110 3
0%
b1101 $
b1101 '
b1101 5
b0 6
#615000
b1 !
b1 2
b11111 3
1%
b1 6
#620000
b1 !
b1 2
b1101 -
b10 (
b11100 3
0%
b1110 $
b1110 '
b1110 5
b0 6
#625000
b10 !
b10 2
b11111 3
1%
b1 6
#630000
b1100 -
b11 (
b11110 3
0%
b1111 $
b1111 '
b1111 5
b0 6
#635000
b11 !
b11 2
b11111 3
1%
b1 6
#640000
0"
0+
0*
01
0)
b100 !
b100 2
b100 -
b0 (
b0 3
0%
b0 $
b0 '
b100 #
b100 &
b100 4
b0 5
b0 6
#645000
b101 !
b101 2
b1 3
1%
b1 6
#650000
b101 -
b0 3
0%
b1 $
b1 '
b1 5
b0 6
#655000
b110 !
b110 2
b11 3
1%
b1 6
#660000
b110 !
b110 2
b110 -
b0 3
0%
b10 $
b10 '
b10 5
b0 6
#665000
b111 !
b111 2
b1 3
1%
b1 6
#670000
1/
1.
b111 -
b0 3
0%
b11 $
b11 '
b11 5
b0 6
#675000
b1000 !
b1000 2
b1111 3
1%
b1 6
#680000
0.
0/
1*
b1000 !
b1000 2
b0 -
b100 (
b1000 3
0%
b100 $
b100 '
b100 5
b0 6
#685000
b1001 !
b1001 2
b1001 3
1%
b1 6
#690000
b1 -
b1000 3
0%
b101 $
b101 '
b101 5
b0 6
#695000
b1010 !
b1010 2
b1011 3
1%
b1 6
#700000
b1010 !
b1010 2
b10 -
b1000 3
0%
b110 $
b110 '
b110 5
b0 6
#705000
b1011 !
b1011 2
b1001 3
1%
b1 6
#710000
1.
b11 -
b1000 3
0%
b111 $
b111 '
b111 5
b0 6
#715000
b1100 !
b1100 2
b1111 3
1%
b1 6
#720000
00
0.
11
0/
0*
b1100 !
b1100 2
b1100 -
b0 (
b0 3
0%
b1000 $
b1000 '
b1000 5
b0 6
#725000
b1101 !
b1101 2
b1 3
1%
b1 6
#730000
b1101 -
b0 3
0%
b1001 $
b1001 '
b1001 5
b0 6
#735000
b1110 !
b1110 2
b11 3
1%
b1 6
#740000
b1110 !
b1110 2
b1110 -
b0 3
0%
b1010 $
b1010 '
b1010 5
b0 6
#745000
b1111 !
b1111 2
b1 3
1%
b1 6
#750000
10
1/
1.
b1111 -
b0 3
0%
b1011 $
b1011 '
b1011 5
b0 6
#755000
1"
b0 !
b0 2
b11111 3
1%
b1 6
#760000
1+
1"
00
1,
0.
01
0/
1*
b0 !
b0 2
b1000 -
b100 (
b11000 3
0%
b1100 $
b1100 '
b1100 5
b0 6
#765000
b1 !
b1 2
b11001 3
1%
b1 6
#770000
b1001 -
b11000 3
0%
b1101 $
b1101 '
b1101 5
b0 6
#775000
b10 !
b10 2
b11011 3
1%
b1 6
#780000
b10 !
b10 2
b1010 -
b11000 3
0%
b1110 $
b1110 '
b1110 5
b0 6
#785000
b11 !
b11 2
b11001 3
1%
b1 6
#790000
1.
b1011 -
b11000 3
0%
b1111 $
b1111 '
b1111 5
b0 6
#795000
b100 !
b100 2
b11111 3
1%
b1 6
#800000
0"
0+
0,
0.
0/
0*
b101 !
b101 2
b101 -
b0 (
b0 3
0%
b0 $
b0 '
b101 #
b101 &
b101 4
b0 5
b0 6
#805000
b110 !
b110 2
b11 3
1%
b1 6
#810000
b100 -
b1 (
b10 3
0%
b1 $
b1 '
b1 5
b0 6
#815000
b111 !
b111 2
b11 3
1%
b1 6
#820000
1/
1.
b111 !
b111 2
b111 -
b0 (
b0 3
0%
b10 $
b10 '
b10 5
b0 6
#825000
b1000 !
b1000 2
b1111 3
1%
b1 6
#830000
1*
b1000 !
b1000 2
0/
1)
0.
b110 -
b1 (
b1110 3
0%
b11 $
b11 '
b11 5
b0 6
#835000
b1001 !
b1001 2
b1111 3
1%
b1 6
#840000
0)
b1001 !
b1001 2
b1 -
b100 (
b1000 3
0%
b100 $
b100 '
b100 5
b0 6
#845000
b1010 !
b1010 2
b1011 3
1%
b1 6
#850000
b0 -
b101 (
b1010 3
0%
b101 $
b101 '
b101 5
b0 6
#855000
b1011 !
b1011 2
b1011 3
1%
b1 6
#860000
1.
b1011 !
b1011 2
b11 -
b100 (
b1000 3
0%
b110 $
b110 '
b110 5
b0 6
#865000
b1100 !
b1100 2
b1111 3
1%
b1 6
#870000
b1100 !
b1100 2
1)
0.
b10 -
b101 (
b1110 3
0%
b111 $
b111 '
b111 5
b0 6
#875000
b1101 !
b1101 2
b1111 3
1%
b1 6
#880000
0"
0+
0)
11
0*
b1101 !
b1101 2
b1101 -
b0 (
b0 3
0%
b1000 $
b1000 '
b1000 5
b0 6
#885000
b1110 !
b1110 2
b11 3
1%
b1 6
#890000
b1100 -
b1 (
b10 3
0%
b1001 $
b1001 '
b1001 5
b0 6
#895000
b1111 !
b1111 2
b11 3
1%
b1 6
#900000
10
1/
1.
b1111 !
b1111 2
b1111 -
b0 (
b0 3
0%
b1010 $
b1010 '
b1010 5
b0 6
#905000
1"
b0 !
b0 2
b11111 3
1%
b1 6
#910000
1+
1*
b0 !
b0 2
00
1"
0/
1)
0.
b1110 -
b1 (
b11110 3
0%
b1011 $
b1011 '
b1011 5
b0 6
#915000
b1 !
b1 2
b11111 3
1%
b1 6
#920000
0)
1,
01
b1 !
b1 2
b1001 -
b100 (
b11000 3
0%
b1100 $
b1100 '
b1100 5
b0 6
#925000
b10 !
b10 2
b11011 3
1%
b1 6
#930000
b1000 -
b101 (
b11010 3
0%
b1101 $
b1101 '
b1101 5
b0 6
#935000
b11 !
b11 2
b11011 3
1%
b1 6
#940000
1.
b11 !
b11 2
b1011 -
b100 (
b11000 3
0%
b1110 $
b1110 '
b1110 5
b0 6
#945000
b100 !
b100 2
b11111 3
1%
b1 6
#950000
b100 !
b100 2
1)
0.
b1010 -
b101 (
b11110 3
0%
b1111 $
b1111 '
b1111 5
b0 6
#955000
b101 !
b101 2
b11111 3
1%
b1 6
#960000
0"
0+
0)
0,
0*
b110 !
b110 2
b110 -
b0 (
b0 3
0%
b0 $
b0 '
b110 #
b110 &
b110 4
b0 5
b0 6
#965000
b111 !
b111 2
b1 3
1%
b1 6
#970000
1/
1.
b111 -
b0 3
0%
b1 $
b1 '
b1 5
b0 6
#975000
b1000 !
b1000 2
b1111 3
1%
b1 6
#980000
1*
0/
0.
1)
b1000 !
b1000 2
b100 -
b10 (
b1100 3
0%
b10 $
b10 '
b10 5
b0 6
#985000
b1001 !
b1001 2
b1101 3
1%
b1 6
#990000
b101 -
b1100 3
0%
b11 $
b11 '
b11 5
b0 6
#995000
b1010 !
b1010 2
b1111 3
1%
b1 6
#1000000
0)
b1010 !
b1010 2
b10 -
b100 (
b1000 3
0%
b100 $
b100 '
b100 5
b0 6
#1005000
b1011 !
b1011 2
b1001 3
1%
b1 6
#1010000
1.
b11 -
b1000 3
0%
b101 $
b101 '
b101 5
b0 6
#1015000
b1100 !
b1100 2
b1111 3
1%
b1 6
#1020000
0.
1)
b1100 !
b1100 2
b0 -
b110 (
b1100 3
0%
b110 $
b110 '
b110 5
b0 6
#1025000
b1101 !
b1101 2
b1101 3
1%
b1 6
#1030000
b1 -
b1100 3
0%
b111 $
b111 '
b111 5
b0 6
#1035000
b1110 !
b1110 2
b1111 3
1%
b1 6
#1040000
11
0)
0*
b1110 !
b1110 2
b1110 -
b0 (
b0 3
0%
b1000 $
b1000 '
b1000 5
b0 6
#1045000
b1111 !
b1111 2
b1 3
1%
b1 6
#1050000
10
1/
1.
b1111 -
b0 3
0%
b1001 $
b1001 '
b1001 5
b0 6
#1055000
1"
b0 !
b0 2
b11111 3
1%
b1 6
#1060000
1+
00
1*
1"
0/
0.
1)
b0 !
b0 2
b1100 -
b10 (
b11100 3
0%
b1010 $
b1010 '
b1010 5
b0 6
#1065000
b1 !
b1 2
b11101 3
1%
b1 6
#1070000
b1101 -
b11100 3
0%
b1011 $
b1011 '
b1011 5
b0 6
#1075000
b10 !
b10 2
b11111 3
1%
b1 6
#1080000
1,
01
0)
b10 !
b10 2
b1010 -
b100 (
b11000 3
0%
b1100 $
b1100 '
b1100 5
b0 6
#1085000
b11 !
b11 2
b11001 3
1%
b1 6
#1090000
1.
b1011 -
b11000 3
0%
b1101 $
b1101 '
b1101 5
b0 6
#1095000
b100 !
b100 2
b11111 3
1%
b1 6
#1100000
0.
1)
b100 !
b100 2
b1000 -
b110 (
b11100 3
0%
b1110 $
b1110 '
b1110 5
b0 6
#1105000
b101 !
b101 2
b11101 3
1%
b1 6
#1110000
b1001 -
b11100 3
0%
b1111 $
b1111 '
b1111 5
b0 6
#1115000
b110 !
b110 2
b11111 3
1%
b1 6
#1120000
0"
0+
1/
0,
1.
0)
0*
b111 !
b111 2
b111 -
b0 (
b0 3
0%
b0 $
b0 '
b111 #
b111 &
b111 4
b0 5
b0 6
#1125000
b1000 !
b1000 2
b1111 3
1%
b1 6
#1130000
1*
b1000 !
b1000 2
0/
1)
0.
b110 -
b1 (
b1110 3
0%
b1 $
b1 '
b1 5
b0 6
#1135000
b1001 !
b1001 2
b1111 3
1%
b1 6
#1140000
b1001 !
b1001 2
b101 -
b10 (
b1100 3
0%
b10 $
b10 '
b10 5
b0 6
#1145000
b1010 !
b1010 2
b1111 3
1%
b1 6
#1150000
b100 -
b11 (
b1110 3
0%
b11 $
b11 '
b11 5
b0 6
#1155000
b1011 !
b1011 2
b1111 3
1%
b1 6
#1160000
1.
0)
b1011 !
b1011 2
b11 -
b100 (
b1000 3
0%
b100 $
b100 '
b100 5
b0 6
#1165000
b1100 !
b1100 2
b1111 3
1%
b1 6
#1170000
b1100 !
b1100 2
1)
0.
b10 -
b101 (
b1110 3
0%
b101 $
b101 '
b101 5
b0 6
#1175000
b1101 !
b1101 2
b1111 3
1%
b1 6
#1180000
b1101 !
b1101 2
b1 -
b110 (
b1100 3
0%
b110 $
b110 '
b110 5
b0 6
#1185000
b1110 !
b1110 2
b1111 3
1%
b1 6
#1190000
b0 -
b111 (
b1110 3
0%
b111 $
b111 '
b111 5
b0 6
#1195000
b1111 !
b1111 2
b1111 3
1%
b1 6
#1200000
10
1/
1.
11
0)
0*
b1111 !
b1111 2
b1111 -
b0 (
b0 3
0%
b1000 $
b1000 '
b1000 5
b0 6
#1205000
1"
b0 !
b0 2
b11111 3
1%
b1 6
#1210000
1+
1*
b0 !
b0 2
00
1"
0/
1)
0.
b1110 -
b1 (
b11110 3
0%
b1001 $
b1001 '
b1001 5
b0 6
#1215000
b1 !
b1 2
b11111 3
1%
b1 6
#1220000
b1 !
b1 2
b1101 -
b10 (
b11100 3
0%
b1010 $
b1010 '
b1010 5
b0 6
#1225000
b10 !
b10 2
b11111 3
1%
b1 6
#1230000
b1100 -
b11 (
b11110 3
0%
b1011 $
b1011 '
b1011 5
b0 6
#1235000
b11 !
b11 2
b11111 3
1%
b1 6
#1240000
1,
1.
01
0)
b11 !
b11 2
b1011 -
b100 (
b11000 3
0%
b1100 $
b1100 '
b1100 5
b0 6
#1245000
b100 !
b100 2
b11111 3
1%
b1 6
#1250000
b100 !
b100 2
1)
0.
b1010 -
b101 (
b11110 3
0%
b1101 $
b1101 '
b1101 5
b0 6
#1255000
b101 !
b101 2
b11111 3
1%
b1 6
#1260000
b101 !
b101 2
b1001 -
b110 (
b11100 3
0%
b1110 $
b1110 '
b1110 5
b0 6
#1265000
b110 !
b110 2
b11111 3
1%
b1 6
#1270000
b1000 -
b111 (
b11110 3
0%
b1111 $
b1111 '
b1111 5
b0 6
#1275000
b111 !
b111 2
b11111 3
1%
b1 6
#1280000
0"
0+
0,
0)
0*
b1000 !
b1000 2
b0 (
b0 3
0%
b0 $
b0 '
b1000 #
b1000 &
b1000 4
b0 5
b0 6
#1285000
b1001 !
b1001 2
b1 3
1%
b1 6
#1290000
b1001 -
b0 3
0%
b1 $
b1 '
b1 5
b0 6
#1295000
b1010 !
b1010 2
b11 3
1%
b1 6
#1300000
b1010 !
b1010 2
b1010 -
b0 3
0%
b10 $
b10 '
b10 5
b0 6
#1305000
b1011 !
b1011 2
b1 3
1%
b1 6
#1310000
1.
b1011 -
b0 3
0%
b11 $
b11 '
b11 5
b0 6
#1315000
b1100 !
b1100 2
b111 3
1%
b1 6
#1320000
00
0.
11
0/
b1100 !
b1100 2
b1100 -
b0 3
0%
b100 $
b100 '
b100 5
b0 6
#1325000
b1101 !
b1101 2
b1 3
1%
b1 6
#1330000
b1101 -
b0 3
0%
b101 $
b101 '
b101 5
b0 6
#1335000
b1110 !
b1110 2
b11 3
1%
b1 6
#1340000
b1110 !
b1110 2
b1110 -
b0 3
0%
b110 $
b110 '
b110 5
b0 6
#1345000
b1111 !
b1111 2
b1 3
1%
b1 6
#1350000
10
1/
1.
b1111 -
b0 3
0%
b111 $
b111 '
b111 5
b0 6
#1355000
1"
b0 !
b0 2
b11111 3
1%
b1 6
#1360000
1"
00
1+
0.
01
0/
1,
b0 !
b0 2
b0 -
b1000 (
b10000 3
0%
b1000 $
b1000 '
b1000 5
b0 6
#1365000
b1 !
b1 2
b10001 3
1%
b1 6
#1370000
b1 -
b10000 3
0%
b1001 $
b1001 '
b1001 5
b0 6
#1375000
b10 !
b10 2
b10011 3
1%
b1 6
#1380000
b10 !
b10 2
b10 -
b10000 3
0%
b1010 $
b1010 '
b1010 5
b0 6
#1385000
b11 !
b11 2
b10001 3
1%
b1 6
#1390000
1.
b11 -
b10000 3
0%
b1011 $
b1011 '
b1011 5
b0 6
#1395000
b100 !
b100 2
b10111 3
1%
b1 6
#1400000
0.
0/
b100 !
b100 2
b100 -
b10000 3
0%
b1100 $
b1100 '
b1100 5
b0 6
#1405000
b101 !
b101 2
b10001 3
1%
b1 6
#1410000
b101 -
b10000 3
0%
b1101 $
b1101 '
b1101 5
b0 6
#1415000
b110 !
b110 2
b10011 3
1%
b1 6
#1420000
b110 !
b110 2
b110 -
b10000 3
0%
b1110 $
b1110 '
b1110 5
b0 6
#1425000
b111 !
b111 2
b10001 3
1%
b1 6
#1430000
1/
1.
b111 -
b10000 3
0%
b1111 $
b1111 '
b1111 5
b0 6
#1435000
b1000 !
b1000 2
b11111 3
1%
b1 6
#1440000
0"
0+
0.
0/
0,
b1001 !
b1001 2
b1001 -
b0 (
b0 3
0%
b0 $
b0 '
b1001 #
b1001 &
b1001 4
b0 5
b0 6
#1445000
b1010 !
b1010 2
b11 3
1%
b1 6
#1450000
b1000 -
b1 (
b10 3
0%
b1 $
b1 '
b1 5
b0 6
#1455000
b1011 !
b1011 2
b11 3
1%
b1 6
#1460000
1.
b1011 !
b1011 2
b1011 -
b0 (
b0 3
0%
b10 $
b10 '
b10 5
b0 6
#1465000
b1100 !
b1100 2
b111 3
1%
b1 6
#1470000
b1100 !
b1100 2
1)
0.
b1010 -
b1 (
b110 3
0%
b11 $
b11 '
b11 5
b0 6
#1475000
b1101 !
b1101 2
b111 3
1%
b1 6
#1480000
0"
0+
0*
0)
11
b1101 !
b1101 2
b1101 -
b0 (
b0 3
0%
b100 $
b100 '
b100 5
b0 6
#1485000
b1110 !
b1110 2
b11 3
1%
b1 6
#1490000
b1100 -
b1 (
b10 3
0%
b101 $
b101 '
b101 5
b0 6
#1495000
b1111 !
b1111 2
b11 3
1%
b1 6
#1500000
10
1/
1.
b1111 !
b1111 2
b1111 -
b0 (
b0 3
0%
b110 $
b110 '
b110 5
b0 6
#1505000
1"
b0 !
b0 2
b11111 3
1%
b1 6
#1510000
1+
1*
b0 !
b0 2
00
1"
0/
1)
0.
b1110 -
b1 (
b11110 3
0%
b111 $
b111 '
b111 5
b0 6
#1515000
b1 !
b1 2
b11111 3
1%
b1 6
#1520000
0*
0)
01
1,
b1 !
b1 2
b1 -
b1000 (
b10000 3
0%
b1000 $
b1000 '
b1000 5
b0 6
#1525000
b10 !
b10 2
b10011 3
1%
b1 6
#1530000
b0 -
b1001 (
b10010 3
0%
b1001 $
b1001 '
b1001 5
b0 6
#1535000
b11 !
b11 2
b10011 3
1%
b1 6
#1540000
1.
b11 !
b11 2
b11 -
b1000 (
b10000 3
0%
b1010 $
b1010 '
b1010 5
b0 6
#1545000
b100 !
b100 2
b10111 3
1%
b1 6
